CHANGES.txt
buildout.cfg
setup.py
src/z3c/__init__.py
src/z3c.relationfieldui.egg-info/PKG-INFO
src/z3c.relationfieldui.egg-info/SOURCES.txt
src/z3c.relationfieldui.egg-info/dependency_links.txt
src/z3c.relationfieldui.egg-info/namespace_packages.txt
src/z3c.relationfieldui.egg-info/not-zip-safe
src/z3c.relationfieldui.egg-info/requires.txt
src/z3c.relationfieldui.egg-info/top_level.txt
src/z3c/relationfieldui/README.txt
src/z3c/relationfieldui/__init__.py
src/z3c/relationfieldui/configure.zcml
src/z3c/relationfieldui/ftesting.zcml
src/z3c/relationfieldui/ftests.py
src/z3c/relationfieldui/interfaces.py
src/z3c/relationfieldui/source.py
src/z3c/relationfieldui/testing.py
src/z3c/relationfieldui/widget.py
src/z3c/relationfieldui/resources/relation.js