Metadata-Version: 1.0
Name: z3c.relationfieldui
Version: 0.5
Summary: A widget for z3c.relationfield.
Home-page: UNKNOWN
Author: Martijn Faassen
Author-email: faassen@startifact.com
License: UNKNOWN
Platform: UNKNOWN
